_openapi_client/__init__.py
_openapi_client/api_client.py
_openapi_client/api_response.py
_openapi_client/configuration.py
_openapi_client/exceptions.py
_openapi_client/py.typed
_openapi_client/rest.py
_openapi_client/api/__init__.py
_openapi_client/api/certs_api.py
_openapi_client/api/cloudstate_api.py
_openapi_client/api/deprecated_api.py
_openapi_client/api/dev_servers_api.py
_openapi_client/api/dns_api.py
_openapi_client/api/domains_api.py
_openapi_client/api/execute_api.py
_openapi_client/api/git_api.py
_openapi_client/api/observability_api.py
_openapi_client/api/web_api.py
_openapi_client/models/__init__.py
_openapi_client/models/access_level.py
_openapi_client/models/access_token_info.py
_openapi_client/models/accessible_repository.py
_openapi_client/models/behavior.py
_openapi_client/models/blob.py
_openapi_client/models/blob_encoding.py
_openapi_client/models/blob_object.py
_openapi_client/models/branch_details.py
_openapi_client/models/commit_object.py
_openapi_client/models/commit_parent.py
_openapi_client/models/commit_tree.py
_openapi_client/models/configure_github_sync_request.py
_openapi_client/models/create_domain_mapping_request.py
_openapi_client/models/create_record_params.py
_openapi_client/models/create_repo_import.py
_openapi_client/models/create_repo_request.py
_openapi_client/models/create_repo_source.py
_openapi_client/models/create_repository_request.py
_openapi_client/models/create_repository_response_success.py
_openapi_client/models/created_token.py
_openapi_client/models/custom.py
_openapi_client/models/custom_build_options.py
_openapi_client/models/deployment_build_options.py
_openapi_client/models/deployment_log_entry.py
_openapi_client/models/deployment_source.py
_openapi_client/models/deployment_state.py
_openapi_client/models/describe_permission_response_success.py
_openapi_client/models/dev_server.py
_openapi_client/models/dev_server_one_of.py
_openapi_client/models/dev_server_request.py
freestyle-0.0.17.dist-info/METADATA
freestyle-0.0.17.dist-info/WHEEL
freestyle-0.0.17.dist-info/top_level.txt
freestyle-0.0.17.dist-info/RECORD
