Metadata-Version: 2.4
Name: freestyle
Version: 0.0.17
Requires-Python: >=3.8
